README.rst
setup.cfg
setup.py
awsrequests/__init__.py
awsrequests/signing.py
awsrequests.egg-info/PKG-INFO
awsrequests.egg-info/SOURCES.txt
awsrequests.egg-info/dependency_links.txt
awsrequests.egg-info/requires.txt
awsrequests.egg-info/top_level.txt