Metadata-Version: 1.0
Name: awsrequests
Version: 0.0.5
Summary: For making signed requests to AWS API Gateway endpoints
Home-page: https://github.com/djcrabhat/aws-requests
Author: ClearDATA
Author-email: support@cleardata.com
License: MIT License
Keywords: AWS API Gateway signing,API Gateway signing,AWS API Gateway requests,API Gateway requests
Platform: UNKNOWN
